alibabacloud_eds_aic20230930/__init__.py
alibabacloud_eds_aic20230930/client.py
alibabacloud_eds_aic20230930/models/__init__.py
alibabacloud_eds_aic20230930/models/_attach_key_pair_request.py
alibabacloud_eds_aic20230930/models/_attach_key_pair_response.py
alibabacloud_eds_aic20230930/models/_attach_key_pair_response_body.py
alibabacloud_eds_aic20230930/models/_authorize_android_instance_request.py
alibabacloud_eds_aic20230930/models/_authorize_android_instance_response.py
alibabacloud_eds_aic20230930/models/_authorize_android_instance_response_body.py
alibabacloud_eds_aic20230930/models/_backup_android_instance_request.py
alibabacloud_eds_aic20230930/models/_backup_android_instance_response.py
alibabacloud_eds_aic20230930/models/_backup_android_instance_response_body.py
alibabacloud_eds_aic20230930/models/_backup_app_request.py
alibabacloud_eds_aic20230930/models/_backup_app_response.py
alibabacloud_eds_aic20230930/models/_backup_app_response_body.py
alibabacloud_eds_aic20230930/models/_backup_file_request.py
alibabacloud_eds_aic20230930/models/_backup_file_response.py
alibabacloud_eds_aic20230930/models/_backup_file_response_body.py
alibabacloud_eds_aic20230930/models/_batch_get_acp_connection_ticket_request.py
alibabacloud_eds_aic20230930/models/_batch_get_acp_connection_ticket_response.py
alibabacloud_eds_aic20230930/models/_batch_get_acp_connection_ticket_response_body.py
alibabacloud_eds_aic20230930/models/_change_cloud_phone_node_request.py
alibabacloud_eds_aic20230930/models/_change_cloud_phone_node_response.py
alibabacloud_eds_aic20230930/models/_change_cloud_phone_node_response_body.py
alibabacloud_eds_aic20230930/models/_check_resource_stock_request.py
alibabacloud_eds_aic20230930/models/_check_resource_stock_response.py
alibabacloud_eds_aic20230930/models/_check_resource_stock_response_body.py
alibabacloud_eds_aic20230930/models/_create_android_instance_group_request.py
alibabacloud_eds_aic20230930/models/_create_android_instance_group_response.py
alibabacloud_eds_aic20230930-4.21.0.dist-info/LICENSE
alibabacloud_eds_aic20230930-4.21.0.dist-info/METADATA
alibabacloud_eds_aic20230930-4.21.0.dist-info/WHEEL
alibabacloud_eds_aic20230930-4.21.0.dist-info/top_level.txt
alibabacloud_eds_aic20230930-4.21.0.dist-info/RECORD
